redis_unique_queue/__init__.py
redis_unique_queue/types.py
redis_unique_queue-0.0.5.dist-info/METADATA
redis_unique_queue-0.0.5.dist-info/WHEEL
redis_unique_queue-0.0.5.dist-info/licenses/LICENSE
redis_unique_queue-0.0.5.dist-info/RECORD
