Metadata-Version: 2.4
Name: redis-unique-queue
Version: 0.0.5
Summary: A module that combines the use of redis in-built data types to build a unique queue for processing and expiry.
Project-URL: Homepage, https://github.com/geonyoro/redis-unique-queue
Project-URL: Issues, https://github.com/geonyoro/redis-unique-queue/issues
Author-email: George Nyoro <geonyoro@gmail.com>
License-Expression: MIT
License-File: LICENSE
Classifier: Development Status :: 5 - Production/Stable
Classifier: Intended Audience :: Developers
Classifier: License :: OSI Approved :: MIT License
Classifier: Operating System :: OS Independent
Classifier: Programming Language :: Python :: 3.8
Classifier: Topic :: Software Development :: Libraries :: Python Modules
Requires-Python: >=3.8
Requires-Dist: redis>=4.6.0
